mpy_devices/__init__.py
mpy_devices/__main__.py
mpy_devices/cli.py
mpy_devices/core.py
mpy_devices/tui.py
mpy_devices-1.1.0.dist-info/METADATA
mpy_devices-1.1.0.dist-info/WHEEL
mpy_devices-1.1.0.dist-info/entry_points.txt
mpy_devices-1.1.0.dist-info/licenses/LICENSE
mpy_devices-1.1.0.dist-info/RECORD
