Metadata-Version: 2.4
Name: mpy-devices
Version: 1.1.0
Summary: Query and monitor MicroPython devices - discover connected devices and check firmware versions
Project-URL: Homepage, https://github.com/andrewleech/mpy-devices
Project-URL: Repository, https://github.com/andrewleech/mpy-devices
Project-URL: Issues, https://github.com/andrewleech/mpy-devices/issues
Author: Andrew Leech
License: MIT
License-File: LICENSE
Keywords: devices,firmware,micropython,serial,usb
Classifier: Development Status :: 4 - Beta
Classifier: Intended Audience :: Developers
Classifier: License :: OSI Approved :: MIT License
Classifier: Programming Language :: Python :: 3
Classifier: Programming Language :: Python :: 3.8
Classifier: Programming Language :: Python :: 3.9
Classifier: Programming Language :: Python :: 3.10
Classifier: Programming Language :: Python :: 3.11
Classifier: Programming Language :: Python :: 3.12
Classifier: Topic :: Software Development :: Embedded Systems
Requires-Python: >=3.8
Requires-Dist: click>=8.0
Requires-Dist: mpremote>=1.20
Requires-Dist: pyserial>=3.5
Requires-Dist: rich>=13.0
Requires-Dist: textual>=0.50
Provides-Extra: dev
Requires-Dist: black>=23.0; extra == 'dev'
Requires-Dist: pytest-cov>=4.0; extra == 'dev'
Requires-Dist: pytest>=7.0; extra == 'dev'
Requires-Dist: ruff>=0.1.0; extra == 'dev'
